LICENSE.txt
MANIFEST.in
README.md
setup.py
p3270/__init__.py
p3270/p3270.cfg
p3270/p3270.py
p3270.egg-info/PKG-INFO
p3270.egg-info/SOURCES.txt
p3270.egg-info/dependency_links.txt
p3270.egg-info/top_level.txt