Metadata-Version: 1.1
Name: p3270
Version: 0.1.2
Summary: Python library to communicate with IBM hosts
Home-page: https://github.com/mstiri/p3270
Author: Mossaab Stiri
Author-email: mossaab.stiri@gmail.com
License: UNKNOWN
Keywords: IBM CICS 3270 TN3270 test automation Mainframe z/OS
Platform: UNKNOWN
Classifier: Intended Audience :: Developers
Classifier: Programming Language :: Python
Classifier: Programming Language :: Python :: 3
Classifier: Programming Language :: Python :: 3 :: Only
Classifier: Operating System :: Unix
Classifier: Operating System :: POSIX :: Linux
Classifier: Topic :: Software Development :: Testing
Classifier: Topic :: Software Development :: Libraries :: Python Modules
Classifier: License :: OSI Approved :: GNU General Public License v3 (GPLv3)
Classifier: Development Status :: 4 - Beta
